Workbook

Sheet Ozet Dashboard
A1: OZET DASHBOARD | Ilerleme ve Efor Takibi
A2: Tum degerler 'Sprint Plani' sayfasindan formullerle otomatik hesaplanir. Bu sayfaya elle deger girmeyin.
A4: PROJE KUNYESI
A5: Proje Adı | B5: Kalori Sayacı + Akıllı Kiler Asistanı (Mobil Uygulama)
A6: Süre | B6: 20 iş günü (4 hafta) - Staj MVP
A7: Ekip | B7: 1 geliştirici (full-stack)
A8: Mobil | B8: Flutter + Dart + Material 3 + Riverpod + go_router + dio
A9: Backend | B9: Python / FastAPI (katmanlı mimari, JWT auth, global hata yönetimi)
A10: İlişkisel DB | B10: SQLite - 21 tablo (kullanıcı, sözlük, kiler+olaylar, kalori, tarif, AI)
A11: Doküman DB | B11: MongoDB Atlas M0 (recipes koleksiyonu)
A12: Birleştirme anahtarı | B12: ingredients.canonical_name <-> recipes.ingredients[].canonical_name
A13: Yapay Zeka | B13: Groq üzerinde LLaMA 3 + RAG mimarisi + llm_cache yanıt önbelleği
A14: Cihaz Üstü AI | B14: Google ML Kit - mobile_scanner ile barkod okuma (ücretsiz, offline)
A15: Dış Veri | B15: Open Food Facts (barkod + besin değeri), Kaggle tarif veri setleri
A16: Hedef Platform | B16: Yalnızca Android (.apk) - geliştirme ortamı Windows, iOS V2'ye alındı
... A18: MVP Kapsam Dışı | B18: Fiş OCR (V3), görsel obje tanıma (V3), sosyal ağ (V3), iOS sürümü (V2)
A20: HAFTALIK EFOR DAGILIMI
A21: Hafta | B21: Görev Sayısı | C21: Toplam Saat | D21: Tamamlanan Saat | E21: İlerleme % | F21: Odak
A22: Hafta 1 | B22: =COUNTIF('Sprint Plani'!$A$4:$A$77,$A22) | C22: =SUMIF('Sprint Plani'!$A$4:$A$77,$A22,'Sprint Plani'!$H$4:$H$77) | D22: =SUMIFS('Sprint Plani'!$H$4:$H$77,'Sprint Plani'!$A$4:$A$77,$A22,'Sprint Plani'!$K$4:$K$77,"Tamamlandı") | E22: =IFERROR($D22/$C22,0) | F22: Mimari, 21 tablolu şema tasarımı, ORM+Alembic, auth, Flutter iskelet, onboarding, malzeme sözlüğü
A23: Hafta 2 | B23: =COUNTIF('Sprint Plani'!$A$4:$A$77,$A23) | C23: =SUMIF('Sprint Plani'!$A$4:$A$77,$A23,'Sprint Plani'!$H$4:$H$77) | D23: =SUMIFS('Sprint Plani'!$H$4:$H$77,'Sprint Plani'!$A$4:$A$77,$A23,'Sprint Plani'!$K$4:$K$77,"Tamamlandı") | E23: =IFERROR($D23/$C23,0) | F23: Kiler CRUD, temel birim, pantry_events olay günlüğü, mobile_scanner barkod, Open Food Facts, kalori sayacı
A24: Hafta 3 | B24: =COUNTIF('Sprint Plani'!$A$4:$A$77,$A24) | C24: =SUMIF('Sprint Plani'!$A$4:$A$77,$A24,'Sprint Plani'!$H$4:$H$77) | D24: =SUMIFS('Sprint Plani'!$H$4:$H$77,'Sprint Plani'!$A$4:$A$77,$A24,'Sprint Plani'!$K$4:$K$77,"Tamamlandı") | E24: =IFERROR($D24/$C24,0) | F24: Üç aşamalı malzeme eşleştirme, aggregation skoru, alerjen filtresi, öğrenen profil, RAG chatbot
A25: Hafta 4 | B25: =COUNTIF('Sprint Plani'!$A$4:$A$77,$A25) | C25: =SUMIF('Sprint Plani'!$A$4:$A$77,$A25,'Sprint Plani'!$H$4:$H$77) | D25: =SUMIFS('Sprint Plani'!$H$4:$H$77,'Sprint Plani'!$A$4:$A$77,$A25,'Sprint Plani'!$K$4:$K$77,"Tamamlandı") | E25: =IFERROR($D25/$C25,0) | F25: Yeşil/kırmızı/gri kartlar, stok düşümü, alışveriş listesi, testler, KVKK, APK, sunum
A26: TOPLAM | B26: =SUM(B22:B25) | C26: =SUM(C22:C25) | D26: =SUM(D22:D25) | E26: =IFERROR(D26/C26,0) | F26: Kapasite 160 saat (20 gün x 8 saat). 6.5 saatlik fazlalık için kesim sırası: W4-T07 > W4-T17 > W3-T16.
A28: DURUM VE ONCELIK DAGILIMI
A29: Kategori | B29: Değer | C29: Adet | D29: Saat | F29: Açıklama
A30: Durum | B30: Yapılacak | C30: =COUNTIF('Sprint Plani'!$K$4:$K$77,$B30) | D30: =SUMIF('Sprint Plani'!$K$4:$K$77,$B30,'Sprint Plani'!$H$4:$H$77) | F30: Henüz başlanmamış görevler
A31: Durum | B31: Devam Ediyor | C31: =COUNTIF('Sprint Plani'!$K$4:$K$77,$B31) | D31: =SUMIF('Sprint Plani'!$K$4:$K$77,$B31,'Sprint Plani'!$H$4:$H$77) | F31: Üzerinde çalışılan görevler
A32: Durum | B32: Tamamlandı | C32: =COUNTIF('Sprint Plani'!$K$4:$K$77,$B32) | D32: =SUMIF('Sprint Plani'!$K$4:$K$77,$B32,'Sprint Plani'!$H$4:$H$77) | F32: Kabul kriteri karşılanmış görevler
A33: Durum | B33: Bloke | C33: =COUNTIF('Sprint Plani'!$K$4:$K$77,$B33) | D33: =SUMIF('Sprint Plani'!$K$4:$K$77,$B33,'Sprint Plani'!$H$4:$H$77) | F33: Dış bağımlılık veya hata nedeniyle duran görevler
A34: Öncelik | B34: Kritik | C34: =COUNTIF('Sprint Plani'!$I$4:$I$77,$B34) | D34: =SUMIF('Sprint Plani'!$I$4:$I$77,$B34,'Sprint Plani'!$H$4:$H$77) | F34: MVP'nin çalışması için zorunlu - asla ertelenmez
A35: Öncelik | B35: Yüksek | C35: =COUNTIF('Sprint Plani'!$I$4:$I$77,$B35) | D35: =SUMIF('Sprint Plani'!$I$4:$I$77,$B35,'Sprint Plani'!$H$4:$H$77) | F35: Ürün değerini belirgin artıran görevler
A36: Öncelik | B36: Orta | C36: =COUNTIF('Sprint Plani'!$I$4:$I$77,$B36) | D36: =SUMIF('Sprint Plani'!$I$4:$I$77,$B36,'Sprint Plani'!$H$4:$H$77) | F36: Kalite ve deneyim iyileştirmeleri
A37: Öncelik | B37: Düşük | C37: =COUNTIF('Sprint Plani'!$I$4:$I$77,$B37) | D37: =SUMIF('Sprint Plani'!$I$4:$I$77,$B37,'Sprint Plani'!$H$4:$H$77) | F37: Süre sıkışırsa ilk feda edilecek görevler
A39: v2 DEGISIKLIK OZETI
A40: 1) Mobil yigin React Native -> FLUTTER. Gerekce: mobile_scanner (ML Kit) kurulumu vision-camera + Expo Dev Client zincirinden cok daha basit; 1 numarali risk (native build hatalari) azaliyor. Dismissible, showModalBottomSheet, showDatePicker, SnackBar yerlesik geldigi icin 3 saat kazanildi.
A41: 2) Hedef platform YALNIZCA ANDROID. Gerekce: gelistirme ortami Windows; iOS derlemesi macOS + Xcode gerektiriyor. iOS surumu V2 backlog'una alindi.
A42: 3) UC YENI GOREV eklendi (yesil satirlar): W2-T02A pantry_events (kiler hareket gunlugu), W3-T02A unmatched_ingredients (kendini iyilestiren sozluk), W4-T12A KVKK veri disa aktarma ve hesap silme. Toplam +3.5 saat.
A43: 4) Veritabani semasi 8 -> 21 TABLO. ingredients normalize sozluk katmani eklendi; yesil/kirmizi/GRI uc durumu ancak bu sayede uretilebiliyor.
A44: 5) Fiziksel Android cihaz olmadigi icin W1-T13'e BarcodeScanner soyutlamasi + FakeBarcodeScanner eklendi; gelistirme cihazdan bagimsiz hale getirildi.
A46: KULLANIM KILAVUZU
A47: Elle doldurulacak TEK alan: 'Sprint Plani' sayfasindaki K sutunu (Durum). Acilir listeden secim yapin.
A48: Ornek: K4 hucresini 'Tamamlandi' yaptiginizda bu sayfadaki ilerleme yuzdeleri otomatik guncellenir.
A49: Renk kodlari: Kirmizi = Kritik oncelik / Bloke, Sari = Yuksek oncelik / Devam Ediyor, Yesil = Tamamlandi.
A50: Sprint Plani'nda YESIL ARKA PLANLI satirlar v2'de eklenen yeni gorevlerdir.
A51: 3. satirdaki filtre oklarindan haftaya, module, oncelige veya duruma gore suzebilirsiniz.

Sheet Sprint Plani
A1: KALORI SAYACI + AKILLI KILER ASISTANI | 20 IS GUNLUK STAJ MVP SPRINT PLANI (v2)
A2: Yigin: Flutter (Dart) + FastAPI + SQLite (21 tablo) + MongoDB + Google ML Kit (mobile_scanner) + Open Food Facts + Groq/LLaMA 3 || Hedef platform: yalnizca Android (.apk) - gelistirme ortami Windows || Kapsam disi: fis OCR ve gorsel obje tanima (V3) || Yesil satirlar = v2'de eklenen yeni gorevler
A3: Hafta | B3: Gün | C3: Görev Kodu | D3: Modül | E3: Atomik Görev Adı | F3: Nasıl Yapılacak / Kullanılacak Teknolojiler | G3: Kabul Kriteri (Definition of Done) | H3: Tahmini Süre (Saat) | I3: Öncelik | J3: Bağımlılık | K3: Durum
A4: Hafta 1 | B4: Gün 1 | C4: W1-T01 | D4: Kurulum & DevOps | E4: Proje Reposu ve Klasör Mimarisinin Kurulması | F4: GitHub'da private repo açılır. Monorepo yapısı: /backend (FastAPI), /mobile (Flutter), /docs (diyagramlar), /data (seed JSON). Python + Dart/Flutter için .gitignore, README taslağı, CONTRIBUTING.md eklenir. Branch stratejisi: main (korumalı) + develop + feature/* . Conventional Commits kuralı belirlenir. | G4: Repoya ilk commit atılmış, develop branch açılmış, 4 klasörlü yapı GitHub'da görünüyor. | H4: 2 | I4: Kritik | J4: - | K4: Yapılacak
A5: Hafta 1 | B5: Gün 1 | C5: W1-T02 | D5: Backend | E5: Python Sanal Ortam ve Bağımlılık Yönetimi | F5: python -m venv .venv ile izole ortam. requirements.txt: fastapi, uvicorn[standard], sqlalchemy, alembic, pydantic, pydantic-settings, python-jose[cryptography], passlib[bcrypt], bcrypt==4.0.1, python-multipart, httpx, motor, python-dotenv, rapidfuzz, pytest, pytest-asyncio. pip freeze ile requirements.lock.txt üretilir. | G5: pip install -r requirements.txt hatasız; uvicorn app.main:app --reload ayağa kalkıyor. | H5: 1.5 | I5: Kritik | J5: W1-T01 | K5: Yapılacak
A6: Hafta 1 | B6: Gün 1 | C6: W1-T03 | D6: Backend | E6: FastAPI Katmanlı Mimari İskeleti | F6: app/ altında core (config, security, exceptions), db (base, session), models, schemas, routers, services klasörleri. pydantic-settings ile .env okuma, CORS middleware, global exception handler (tutarlı {code, message} hata formatı), /health ve /api/v1 versiyonlaması, Swagger UI. | G6: GET /health 200 dönüyor; /docs açılıyor; olmayan yol {code, message} formatında 404 dönüyor. | H6: 2.5 | I6: Kritik | J6: W1-T02 | K6: Yapılacak
A7: Hafta 1 | B7: Gün 1-2 | C7: W1-T04 | D7: Veritabanı | E7: İlişkisel Şema (SQLite) E-R Modellemesi - 21 Tablo | F7: dbdiagram.io ile DBML yazılıp E-R modeli çizilir. 21 tablo, 6 grup: kullanıcı (6), sözlük/katalog (5), kiler+alışveriş (3), kalori (2), tarif etkileşimi (3), chatbot/AI (3). Üç anahtar tasarım ilkesi belirlenir: (1) ingredients normalize sözlük katmanı SQLite ile MongoDB arasındaki birleştirme anahtarı, (2) miktarlar tek temel birimde saklanır (g/ml/adet), (3) geçmiş kayıtlar anlık görüntü (snapshot) tutar. PK/FK, UNIQUE(barcode), UNIQUE(canonical_name), CHECK(quantity_base>=0), 1:1 / 1:N / N:N ilişkiler ve indeks kararları verilir. | G7: docs/er-diagram.png + docs/schema.dbml + docs/schema-notes.md repoda; 21 tablo ve 3 ilişki tipi de diyagramda. | H7: 2.5 | I7: Kritik | J7: W1-T01 | K7: Yapılacak
A8: Hafta 1 | B8: Gün 2 | C8: W1-T05 | D8: Veritabanı | E8: SQLAlchemy ORM Modellerinin Yazılması (21 Model) | F8: models/ altında User, UserProfile, DietTag, Allergen, Category, Ingredient, IngredientAlias, UnmatchedIngredient, Product, PantryItem, PantryEvent, ShoppingListItem, MealLog, WeightLog, RecipeFeedback, RecipeFavorite, UserTasteWeight, ChatConversation, ChatMessage, LlmCache + 2 N:N bağlantı tablosu. relationship() + back_populates, cascade='all, delete-orphan', Enum(native_enum=False) ile TEXT+CHECK. KRİTİK: session.py'ye PRAGMA foreign_keys=ON event listener eklenir (SQLite'ta FK zorlaması varsayılan KAPALI). | G8: Tüm modeller import ediliyor; create_all ile 21 tablo oluşuyor; kullanıcı silinince ilişkili kayıtlar CASCADE ile siliniyor. | H8: 3 | I8: Kritik | J8: W1-T04 | K8: Yapılacak
A9: Hafta 1 | B9: Gün 2 | C9: W1-T06 | D9: Veritabanı | E9: Alembic Migration Altyapısı | F9: alembic init, env.py'de target_metadata bağlanır ve render_as_batch=True ayarlanır (SQLite'ın ALTER TABLE kısıtı için ZORUNLU). İlk autogenerate migration üretilip upgrade head çalıştırılır. | G9: alembic upgrade head hatasız; kalori.db ilk kez oluşuyor; versions/ altında migration var. | H9: 1.5 | I9: Yüksek | J9: W1-T05 | K9: Yapılacak
A10: Hafta 1 | B10: Gün 2 | C10: W1-T07 | D10: Backend | E10: Pydantic Şemaları (Request / Response DTO) | F10: schemas/ altında Create/Update/Read ayrımıyla DTO'lar. from_attributes=True, alan doğrulamaları (quantity>0, birim enum, e-posta), ortak ErrorResponse ve generic Page[T] sayfalama şeması. | G10: Swagger'da tüm şemalar doğru; hatalı payload {code:'validation_error'} ile 422 dönüyor. | H10: 2 | I10: Yüksek | J10: W1-T05 | K10: Yapılacak
A11: Hafta 1 | B11: Gün 2-3 | C11: W1-T08 | D11: Auth | E11: JWT Tabanlı Kimlik Doğrulama | F11: passlib+bcrypt ile şifre hash, python-jose ile access token (30 dk) + refresh token. /auth/register, /auth/login, /auth/me. OAuth2PasswordBearer + get_current_user dependency ile korumalı rotalar. | G11: Kayıt -> giriş -> korumalı endpoint akışı çalışıyor; token'sız istek 401 dönüyor. | H11: 2.5 | I11: Kritik | J11: W1-T07 | K11: Yapılacak
A12: Hafta 1 | B12: Gün 3 | C12: W1-T09 | D12: Veritabanı | E12: MongoDB Atlas (Ücretsiz M0) Kurulumu ve Bağlantı | F12: Atlas M0 cluster, IP whitelist, DB kullanıcısı. Backend'de motor (async) ile bağlantı havuzu; connection string .env'den. FastAPI lifespan içinde açılıp kapatılır. | G12: Uygulama açılışında Mongo ping başarılı; bağlantı bilgisi koda gömülü değil. | H12: 1.5 | I12: Kritik | J12: W1-T03 | K12: Yapılacak
A13: Hafta 1 | B13: Gün 3 | C13: W1-T10 | D13: Veritabanı | E13: NoSQL Tarif Koleksiyon Şeması (MongoDB) | F13: recipes koleksiyonu: _id, title, slug, image_url, ingredients[{name, canonical_name, quantity, unit, optional}], steps[], calories_per_serving, macros{protein,carb,fat,fiber}, servings, prep_time, cook_time, difficulty, diet_tags[], allergens[], cuisine. $jsonSchema validator + canonical_name, diet_tags, calories_per_serving üzerine index. | G13: Şema validator aktif; eksik alanlı doküman reddediliyor; index'ler oluşturulmuş. | H13: 2 | I13: Kritik | J13: W1-T09 | K13: Yapılacak
A14: Hafta 1 | B14: Gün 3 | C14: W1-T11 | D14: Veri | E14: Tarif Seed Verisinin Hazırlanması (100+ Tarif) | F14: Kaggle Recipe Ingredients Dataset / RecipeNLG ve telifsiz kaynaklardan veri; Pandas ile temizlik (küçük harf, trim, birim ayrıştırma, mükerrer temizliği). Türk mutfağından en az 40 tarif manuel eklenir (telif riski nedeniyle adımlar yeniden yazılır). /data/recipes_seed.json -> mongoimport. | G14: MongoDB'de en az 100 geçerli tarif; hepsinde kalori, porsiyon ve canonical_name'li malzeme dizisi dolu. | H14: 2.5 | I14: Kritik | J14: W1-T10 | K14: Yapılacak
A15: Hafta 1 | B15: Gün 3 | C15: W1-T12 | D15: Veri | E15: Malzeme Sözlüğü ve Birim Tablosunun Veritabanına Seed'lenmesi | F15: /data/ingredients_seed.json hazırlanıp ingredients + ingredient_aliases + categories tablolarına yüklenir (JSON dosyası artık sadece seed kaynağı, çalışma zamanı kaynağı DB'dir). Her malzeme için: canonical_name, display_name, kategori, temel birim, grams_per_piece (1 soğan ~150 g), ml_to_gram_factor (yoğunluk), cooked_yield_factor (çiğ pirinç -> pilav), 100 g besin değerleri, avg_shelf_life_days, is_staple. Birim dönüşüm fonksiyonu yazılır. | G15: En az 150 malzeme + 300 alias DB'de; birim dönüşüm fonksiyonu 20+ pytest vakasından geçiyor. | H15: 2.5 | I15: Kritik | J15: W1-T11 | K15: Yapılacak
... A77: Hafta 4 | B77: Gün 20 | C77: W4-T17 | D77: Tampon | E77: Tampon Süre / Kritik Hata Payı | F77: Beklenmedik native build hataları, API kotası, cihaz uyumsuzluğu gibi riskler için ayrılan zaman payı. Kullanılmazsa V2 backlog'undan bir madde çekilir (öncelik: israf raporu ekranı). | G77: Plan sapması yaşanmadan teslim tamamlandı. | H77: 2 | I77: Orta | J77: - | K77: Yapılacak
A78: TOPLAM | H78: =SUM(H4:H77) | I78: =COUNTA(C4:C77)&" görev"
A80: KAPASITE: 20 is gunu x 8 saat = 160 saat. Plan toplami 166.5 saat, yani 6.5 saat fazla. Sikisma olursa feda edilecek maddeler SIRASIYLA: W4-T07 SKT bildirimi (Dusuk, 2 saat), W4-T17 tampon (Orta, 2 saat), W3-T16 algoritma olcumu (Orta, 2 saat). Ucu de cikarilirsa plan 160.5 saate iner.
A81: v2 DEGISIKLIKLERI: (1) Mobil yigin React Native -> Flutter. (2) Hedef platform yalnizca Android; iOS V2'ye alindi. (3) Uc yeni gorev eklendi: W2-T02A pantry_events, W3-T02A unmatched_ingredients, W4-T12A KVKK veri imhasi. (4) Veritabani semasi 8 -> 21 tablo. (5) Flutter'in yerlesik bilesenleri sayesinde W1-T15, W2-T07, W2-T08, W2-T09, W2-T10 sureleri toplam 3 saat kisaldi.
A82: ELLE DOLDURULACAK TEK ALAN: K sutunu (Durum). Acilir listeden secim yapin; ornek: K4 -> 'Tamamlandi'. Ozet Dashboard otomatik guncellenir.

Sheet V2-V3 Backlog
A1: KAPSAM DISI OZELLIKLER | V2 ve V3 YOL HARITASI
A2: MVP'den bilincli olarak cikarilan maddeler. Her biri neden ertelendigi, nasil yapilacagi ve maliyetiyle birlikte.
A3: Sürüm | B3: Öncelik | C3: Modül | D3: Özellik | E3: Neden MVP'de Değil? | F3: Nasıl Yapılacak / Teknoloji | G3: Tahmini Süre | H3: Maliyet Etkisi
A4: V2 | B4: Çok Yüksek | C4: Raporlama | D4: Gıda İsrafı ve Tasarruf Raporu | E4: MVP'de veri toplama altyapısı (pantry_events) kuruldu; raporlama ekranı zaman almasın diye ertelendi. | F4: pantry_events tablosundaki bozuldu_atildi olayları ingredients.avg_price_per_100g ile çarpılarak aylık israf raporu üretilir: 'Bu ay 1.2 kg gıda, ~340 TL israf ettin'. Grafik + haftalık karşılaştırma. | G4: 1 hafta | H4: 0 $ - veri zaten toplanıyor
A5: V2 | B5: Çok Yüksek | C5: Kiler | D5: Öngörülü Alışveriş Listesi (Tüketim Hızı) | E5: Anlamlı sonuç için en az 2-3 haftalık kullanım verisi birikmesi gerekiyor. | F5: Son 30 günün tuketildi_* olaylarından malzeme bazlı günlük tüketim hızı hesaplanır; 'haftada ~200 g mercimek tüketiyorsun, 5 gün sonra bitecek' tahmini üretilir ve ürün BİTMEDEN listeye eklenir (source='ongoru'). Rakiplerin hiçbirinde yok. | G5: 1 hafta | H5: 0 $
A6: V2 | B6: Yüksek | C6: AI | D6: Haftalık Beslenme Özeti (AI Koç) | E6: LLM altyapısı W3'te kuruluyor; özet katmanı MVP kapsamını şişirirdi. | F6: meal_logs + pantry_events + weight_logs verisi haftalık olarak özetlenip LLM'e verilir: 'Bu hafta protein hedefinin %70'indesin, akşam öğünlerin geç' gibi kişisel geri bildirim. weekly_reports tablosu eklenir. | G6: 1-2 hafta | H6: LLM: ~1-2 $/ay (önbellekli)
A7: V2 | B7: Yüksek | C7: Kullanıcı | D7: Hane Paylaşımı (Ortak Kiler) | E7: Kiler gerçekte evsel bir kaynak ama tek kullanıcılık model 20 günlük planı basitleştiriyor. Geçiş maliyeti düşük olduğu için bilinçli ertelendi. | F7: households + household_members tabloları eklenir; pantry_items ve shopping_list_items'a household_id sütunu açılır; her mevcut kullanıcı için tek kişilik hane oluşturulup geriye dönük doldurulur. Tek migration. | G7: 4-5 gün | H7: 0 $
A8: V2 | B8: Yüksek | C8: Kiler | D8: Gelişmiş SKT Takibi ve Parti (Batch) Yönetimi | E8: MVP'de kullanıcı başına malzeme başına tek satır tutuluyor; farklı SKT'li partiler birleşiyor. | F8: pantry_batches tablosu eklenir; aynı malzemenin farklı tarihli alımları ayrı satırda tutulur, tüketimde FIFO (ilk giren ilk çıkar) uygulanır. SKT bildirimi parti bazında çalışır. | G8: 1 hafta | H8: 0 $
A9: V2 | B9: Orta | C9: AI | D9: Haftalık Otomatik Yemek Planı | E9: Öneri motorunun tekil tarif seviyesinde doğrulanması önce gelir. | F9: Kalori hedefi, kiler ve tercihler baz alınarak 7 günlük menü üretilir; eksik malzemeler tek seferde alışveriş listesine dökülür. meal_plans + meal_plan_items tabloları. | G9: 1-2 hafta | H9: LLM: ~1-3 $/ay
A10: V2 | B10: Orta | C10: Oyunlaştırma | D10: Tasarruf Rozetleri ve Seri (Streak) | E10: Çekirdek döngünün tuttuğu doğrulanmadan elde tutma özelliği eklemek erken. | F10: İsraf oranı, kiler kullanım oranı ve günlük kayıt serisinden rozetler; paylaşılabilir haftalık özet kartı. user_achievements + user_streaks tabloları. | G10: 1 hafta | H10: 0 $
A11: V2 | B11: Orta | C11: Kalori | D11: Su Takibi + Adım/Egzersiz Entegrasyonu | E11: Kalori dengesinin ikinci yarısı; MVP'de alım tarafına odaklanıldı. | F11: Health Connect (Android) ile adım ve yakılan kalori okunur, günlük hedefe eklenir. Su takibi basit sayaç widget'ı. water_logs + activity_logs tabloları. | G11: 1 hafta | H11: 0 $
A12: V2 | B12: Yüksek | C12: Altyapı | D12: Çevrimdışı (Offline-First) Mod | E12: MVP'de internet varsayımıyla ilerlemek geliştirme hızını iki katına çıkarır. Ama mutfakta bağlantı zayıf olur. | F12: Cihazda drift/sqflite yerel kopya, değişikliklerin kuyruğa alınması ve bağlantı gelince çakışma çözümlemeli (son yazan kazanır + versiyon) senkronizasyon. | G12: 2 hafta | H12: 0 $
A13: V2 | B13: Orta | C13: Platform | D13: iOS Sürümü ve Mağaza Yayını | E13: Geliştirme ortamı Windows; iOS derlemesi macOS + Xcode gerektiriyor. Staj teslimi için .apk yeterli. | F13: Mac erişimi veya Codemagic/GitHub Actions macOS runner ile bulut derleme. Ardından geliştirici hesapları, gizlilik politikası, veri güvenliği formu, ekran görüntüleri, TestFlight ve inceleme süreci. | G13: 1-2 hafta | H13: Apple 99 $/yıl + Google 25 $ tek seferlik
A14: V2 | B14: Orta | C14: AI | D14: Semantik Arama (Embedding / Vektör Veritabanı) | E14: MVP'de üç aşamalı eşleştirme (canonical + alias + rapidfuzz) yeterli doğruluğu veriyor. | F14: Tarif ve malzeme metinleri embedding'e çevrilir (sentence-transformers), Chroma / pgvector'da saklanır. 'Anneannemin yaptığı gibi bir şey' türü bulanık sorgular desteklenir. | G14: 1-2 hafta | H14: Açık kaynak model: 0 $
... A20: V3 | B20: Düşük | C20: Ticari | D20: Online Market Entegrasyonu | E20: Yazılım işi değil, iş geliştirme işi. Anlaşma gerektirir. | F20: Alışveriş listesi doğrudan online markete gönderilir. Ticari olarak en değerli özellik (komisyon modeli). | G20: Belirsiz | H20: Anlaşmaya bağlı

Sheet Maliyet Analizi
A1: MALIYET ANALIZI VE TASARRUF STRATEJILERI
A2: Iki senaryo: (1) hazir bulut servisleriyle optimize EDILMEMIS kurulum, (2) acik kaynak + ucretsiz katman ile OPTIMIZE kurulum.
A3: Maliyet Kalemi | B3: Açıklama | C3: Optimize Edilmemiş Aylık ($) | D3: Ucuza Çözüm / Alternatif | E3: Optimize Aylık ($) | F3: Yıllık Tasarruf ($) | G3: Staj MVP'sinde Gerekli mi?
A4: Sunucu / Backend Barındırma | B4: FastAPI uygulamasının çalıştığı VPS veya PaaS | C4: 12 | D4: Render / Railway / Fly.io ücretsiz katmanı; ya da Supabase (BaaS) | E4: 0 | F4: =(C4-E4)*12 | G4: Evet
A5: Yönetilen Veritabanı | B5: PostgreSQL / MongoDB barındırma | C5: 15 | D5: MongoDB Atlas M0 (ücretsiz, 512 MB) + SQLite dosya veritabanı | E5: 0 | F5: =(C5-E5)*12 | G5: Evet
A6: LLM / Chatbot API | B6: Sohbet asistanının token maliyeti (GPT-4o-mini ile aylık 20-50 $) | C6: 35 | D6: Groq üzerinden LLaMA 3 + llm_cache yanıt önbelleği + kullanıcı başına günlük limit | E6: 2 | F6: =(C6-E6)*12 | G6: Evet
A7: Barkod Tanıma | B7: Bulut görüntü işleme servisi ile barkod çözümleme | C7: 10 | D7: mobile_scanner (Google ML Kit) ile cihaz üzerinde - ücretsiz ve offline | E7: 0 | F7: =(C7-E7)*12 | G7: Evet
A8: Gıda / Barkod Veritabanı | B8: FatSecret veya Nutritionix ücretli plan | C8: 20 | D8: Open Food Facts açık veritabanı (ODbL) + kullanıcı katkılı ürün havuzu | E8: 0 | F8: =(C8-E8)*12 | G8: Evet
A9: Fiş Okuma (OCR) | B9: Google Cloud Vision / AWS Textract (1000 istek ~1.5 $) | C9: 15 | D9: Cihaz üstü ML Kit Text Recognition veya Tesseract (ücretsiz) | E9: 0 | F9: =(C9-E9)*12 | G9: Hayır (V3)
A10: Görsel Depolama / CDN | B10: Tarif ve ürün görsellerinin barındırılması | C10: 5 | D10: Unsplash/Pexels doğrudan bağlantı + cached_network_image ile cihazda önbellek | E10: 0 | F10: =(C10-E10)*12 | G10: Evet
A11: Push Bildirim | B11: Bildirim altyapısı | C11: 5 | D11: flutter_local_notifications ile cihazda yerel bildirim (sunucu gerekmez) | E11: 0 | F11: =(C11-E11)*12 | G11: Kısmen
A12: Hata İzleme / Log | B12: Sentry veya benzeri APM aracı | C12: 26 | D12: Sentry ücretsiz katmanı (5k olay/ay) | E12: 0 | F12: =(C12-E12)*12 | G12: Kısmen
A13: Alan Adı + SSL | B13: Backend için alan adı ve sertifika | C13: 1.5 | D13: Cloudflare ücretsiz SSL + ucuz .com alan adı | E13: 1.5 | F13: =(C13-E13)*12 | G13: Hayır
A14: Google Play Hesabı | B14: Tek seferlik 25 $ (ilk yıla yayıldı) | C14: 2.08 | D14: Zorunlu - staj teslimi için gerekmez | E14: 2.08 | F14: =(C14-E14)*12 | G14: Hayır (V2)
A15: Apple Developer Hesabı | B15: Yıllık 99 $ | C15: 8.25 | D15: iOS V2'ye alındı; Windows'ta derlenemiyor | E15: 8.25 | F15: =(C15-E15)*12 | G15: Hayır (V2)
A16: TOPLAM | B16: Aylık toplam / yıllık toplam tasarruf | C16: =SUM(C4:C15) | D16: Optimize kurulumda aylık gider neredeyse sıfırlanır | E16: =SUM(E4:E15) | F16: =SUM(F4:F15)
A18: STAJ (MVP) SENARYOSU
A19: Staj süresince zorunlu aylık gider ($) | B19: =SUMIF(G4:G15,"Evet",E4:E15) | C19: Sadece MVP'de gerekli kalemlerin optimize maliyeti - ücretsiz katmanlarla neredeyse sıfır
A20: Aynı kalemlerin optimize edilmemiş hali ($) | B20: =SUMIF(G4:G15,"Evet",C4:C15) | C20: Hazır bulut servisleriyle gidilseydi ödenecek aylık tutar
A21: Aylık tasarruf ($) | B21: =B20-B19 | C21: İkisinin farkı - maliyet optimizasyonunun somut karşılığı
A23: VARSAYIMLAR: Tutarlar USD cinsindendir; tek gelistirici ve dusuk trafik (gunluk <1000 istek) varsayimiyla tahmin edilmistir.
A24: Kaynak: proje analizinde optimize edilmemis senaryo icin aylik 100-200 $ ongoruluyordu; buradaki kalem kirilimi o araligi acar.
A25: MALIYET DUSURME TEKNIKLERI: (1) On-device isleme - barkod ve OCR buluta gonderilmez, ML Kit ile telefonda calisir. (2) BaaS / ucretsiz katman - kendi sunucunu yonetme. (3) Acik kaynak LLM - Groq uzerinde LLaMA 3. (4) Onbellekleme - llm_cache ile ayni soru API'ye gitmeden yanitlanir. (5) Acik veri - Open Food Facts ile 0 $ urun veritabani. (6) Kural tabanli oneri - derin ogrenme yerine SQL/NoSQL filtreleme, GPU maliyeti sifir. (7) Android-only teslim - Apple 99 $/yil ertelendi.

Sheet Veri Kaynaklari
A1: VERI ELDE ETME PLANI | Kaynaklar, Lisanslar ve Isleme Adimlari
A2: Barkod/besin degerleri, yemek tarifleri, gorseller ve malzeme sozlugu icin veri kaynaklari.
A3: Veri Türü | B3: Kaynak | C3: Erişim / Lisans | D3: Nasıl Alınacak ve İşlenecek | E3: Maliyet | F3: Risk / Dikkat Edilecek Nokta
A4: Barkod + besin değeri | B4: Open Food Facts | C4: Ücretsiz, açık veri (ODbL) | D4: REST API (api/v2/product/{barcode}.json) ile anlık sorgu; sonuç products tablosuna önbelleklenir. Ayrıca toplu dump indirilip yerel kopya tutulabilir. serving_size ve fiber/sugar/sodium alanları da kaydedilir. | E4: 0 $ | F4: Türk yerel ürünlerinde kapsam boşluğu olabilir; eksikler kullanıcı katkısıyla (source='user') doldurulur.
A5: Barkod (yedek kaynak) | B5: FatSecret Platform API | C5: Freemium | D5: OAuth ile kimlik doğrulama, ürün ve besin sorgusu. Open Food Facts'te bulunamayan barkodlar için ikincil kaynak. | E5: 0 $ (kota içinde) | F5: Kota aşımında ücretlendirme; atıf zorunluluğu var.
A6: Besin değeri referansı | B6: USDA FoodData Central | C6: Ücretsiz, kamu malı | D6: Toplu veri indirilip temel gıdaların (pirinç, mercimek, tavuk) 100 g besin değerleri ingredients tablosuna aktarılır. | E6: 0 $ | F6: ABD odaklı; Türk mutfağı porsiyonlarıyla birebir örtüşmeyebilir.
A7: Yemek tarifleri (toplu) | B7: Kaggle - Recipe Ingredients Dataset / RecipeNLG | C7: Araştırma / açık lisans (koşulları kontrol edilmeli) | D7: CSV indirilir, Pandas ile temizlenir: küçük harfe çevirme, trim, mükerrer temizliği, malzeme-miktar-birim ayrıştırma, canonical_name eşlemesi. Sonuç JSON'a çevrilip mongoimport ile yüklenir. | E7: 0 $ | F7: Lisans koşulları ticari kullanımı sınırlayabilir; yayın öncesi doğrulanmalı.
A8: Türk mutfağı tarifleri | B8: Telifsiz / açık lisanslı kaynaklar + manuel giriş | C8: Kaynak bazında değişir | D8: Yalnızca robots.txt izin veren ve telif içermeyen kaynaklardan BeautifulSoup ile kazıma; Pandas ile temizlik. Kritik 40 tarif elle girilerek kalite garanti altına alınır. | E8: 0 $ | F8: TELİF RİSKİ: Tarif metni telif korumasına girebilir. En güvenlisi malzeme listesinden yola çıkıp adımları kendin yazmaktır.
A9: Tarif görselleri | B9: Unsplash / Pexels API | C9: Ücretsiz, atıf ile | D9: Tarif başlığına göre API'den görsel çekilip URL olarak saklanır; cihazda cached_network_image ile önbelleklenir. Dosya barındırma maliyeti oluşmaz. | E9: 0 $ | F9: Alakasız görsel gelebilir; kritik tariflerde elle seçim yapılmalı.
A10: Malzeme sözlüğü + birim tablosu | B10: Manuel üretim (proje içi) | C10: Proje mülkiyeti | D10: Tarif veri setindeki malzeme adları frekansa göre sıralanır, ilk 150-200 tanesi canonical isimlere elle eşlenir ve ingredients + ingredient_aliases tablolarına seed edilir. grams_per_piece, ml_to_gram_factor, cooked_yield_factor değerleri doldurulur. | E10: 0 $ | F10: PROJENİN EN KRİTİK VERİ VARLIĞI. Eksik olursa tüm eşleştirme algoritması bozulur. W3-T02A ile kendi kendini büyütür.
A11: Eşleşmeyen malzemeler | B11: Uygulamanın kendisi (unmatched_ingredients) | C11: Proje mülkiyeti | D11: Eşleştirilemeyen her metin normalize edilip tabloya yazılır ve sayılır. Hafta sonu frekansa göre en sık 20 kayıt sözlüğe eklenir. | E11: 0 $ | F11: Sözlüğün büyüme motoru. V3 fiş OCR için de aynı mekanizma kullanılır.
A12: Kullanıcı verisi | B12: Uygulama içi onboarding + kullanım logları | C12: Kullanıcı açık rızası ile | D12: Onboarding anketi (diyet, alerjen, hedef, sevilen yemekler) + davranış logları (beğeni, yapılan tarif, kiler hareketleri) toplanır ve öneri skorlamasını besler. | E12: 0 $ | F12: KVKK: Aydınlatma metni, açık rıza ve veri silme hakkı zorunlu. Sağlık verisi ÖZEL NİTELİKLİ kişisel veridir. W4-T12A ile export/silme uçları yazılır.

Sheet Veritabani Semasi
A1: VERITABANI SEMASI | 21 Tablo | SQLite (iliskisel) + MongoDB (dokuman)
A2: Birlestirme anahtarlari: ingredients.canonical_name <-> recipes.ingredients[].canonical_name ve recipe_id (TEXT) <-> recipes._id
A3: Katman | B3: Grup | C3: Tablo / Koleksiyon | D3: Alan | E3: Tip / Kısıt | F3: Açıklama
A4: SQLite | B4: A. Kullanıcı | C4: users | D4: id | E4: INTEGER PK | F4: Otomatik artan birincil anahtar
A5: SQLite | B5: A. Kullanıcı | C5: users | D5: email | E5: TEXT UNIQUE NOT NULL | F5: Giriş kimliği; küçük harfe normalize edilir
A6: SQLite | B6: A. Kullanıcı | C6: users | D6: hashed_password | E6: TEXT NOT NULL | F6: bcrypt ile hash; düz metin ASLA saklanmaz
A7: SQLite | B7: A. Kullanıcı | C7: users | D7: onboarding_completed | E7: BOOLEAN | F7: Anketin tekrar gösterilmemesi için
A8: SQLite | B8: A. Kullanıcı | C8: users | D8: is_active / created_at / updated_at | E8: BOOLEAN / DATETIME | F8: Denetim alanları
A9: SQLite | B9: A. Kullanıcı | C9: user_profiles | D9: user_id | E9: INTEGER FK UNIQUE | F9: users ile 1:1; ON DELETE CASCADE
A10: SQLite | B10: A. Kullanıcı | C10: user_profiles | D10: birth_year | E10: INTEGER | F10: Yaş yerine doğum yılı - veri bayatlamaz
A11: SQLite | B11: A. Kullanıcı | C11: user_profiles | D11: gender / height_cm / weight_kg | E11: TEXT / REAL | F11: BMR hesabının girdileri
A12: SQLite | B12: A. Kullanıcı | C12: user_profiles | D12: activity_level | E12: TEXT CHECK | F12: sedanter / hafif / orta / yuksek / cok_yuksek
A13: SQLite | B13: A. Kullanıcı | C13: user_profiles | D13: goal | E13: TEXT CHECK | F13: kilo_verme / koruma / kilo_alma -> hedefe -/+500 kcal
A14: SQLite | B14: A. Kullanıcı | C14: user_profiles | D14: bmr / tdee / daily_calorie_target | E14: REAL | F14: Mifflin-St Jeor ile hesaplanır (W1-T20)
... A86: MongoDB | B86: G. Tarifler | C86: recipes | D86: cuisine | E86: String | F86: turk / italyan / uzakdogu - öğrenen profil bu etiketi kullanır
A89: SQLITE TUZAKLARI (W1-T05 / W1-T06'da mutlaka uygulanacak):
A90: 1) Foreign key zorlamasi VARSAYILAN OLARAK KAPALI. session.py'ye 'PRAGMA foreign_keys=ON' event listener eklenmezse ON DELETE CASCADE calismaz ve KVKK veri imhasi saglanamaz.
A91: 2) Native ENUM yok. SQLAlchemy'de Enum(..., native_enum=False) ile TEXT + CHECK kisiti olarak uretilir.
A92: 3) ALTER TABLE cok kisitli. Alembic env.py icinde render_as_batch=True ZORUNLU; yoksa 3. haftada sutun eklerken migration patlar.
A93: 4) Native DATE tipi yok. SQLAlchemy Date/DateTime tipleri kullanilmali, elle string yazilmamali.

Sheet Rakip Analizi
A1: RAKIP ANALIZI VE PAZARDAKI BOSLUKLAR
A2: Rakipler ya kalori sayiyor ya tarif veriyor. Bu uygulama 'Mutfak Envanteri + Hedef Kalori + Gida Israfi' kesisiminde calisir.
A3: Rakip Uygulama | B3: Güçlü Yönleri | C3: Zayıf Yönleri (Senin Fırsatın) | D3: Bu Projede Nasıl Fark Yaratılıyor?
A4: MyFitnessPal / Yazio | B4: Dev kalori ve barkod veritabanı, olgun kullanıcı kitlesi, güçlü makro takibi ve alışkanlık serileri. | C4: 'Evde ne var, ne pişirebilirim?' mantığı sıfır. Sadece yediğini girersin; kiler/envanter yönetimi yok. Gıda israfına dair hiçbir şey sunmaz. | D4: Kiler envanteri birinci sınıf özellik: barkodla giren ürün stoktan düşer, eşik altına inince alışveriş listesine düşer. Her hareket pantry_events'e yazıldığı için israf raporu ve tüketim hızı tahmini üretilebilir.
A5: SuperCook / Yummly | B5: Eldeki malzemelere göre çok iyi tarif eşleştirme, geniş tarif havuzu, malzeme bazlı arama. | C5: Kalori ve makro besin takibi çok zayıf. Alışveriş fişi tarama gibi otomatik envanter araçları yok; malzemeleri elle işaretlemek zahmetli. | D5: Malzeme girişi barkod (MVP) ve ileride fiş OCR (V3) ile otomatikleşir. Tarif önerisi kalan günlük kaloriye, diyet tercihine ve alerjenlere göre süzülür.
A6: FatSecret | B6: Topluluk desteği, ücretsiz kullanım, geniş gıda veritabanı ve kilo günlüğü. | C6: Kişiselleştirilmiş akıllı asistan (chatbot) deneyimi yok; arayüz eski ve öneri motoru pasif. | D6: Doğal dilde konuşan RAG tabanlı asistan: 'Bugün hafif bir şey yemek istiyorum' -> kilerdeki malzeme + kalan kalori + tercihlerle GERÇEK tarif önerisi (uydurma yok, yalnızca veritabanındaki tarifler).
A7: Yerel tarif uygulamaları | B7: Türkçe içerik zenginliği, yerel mutfağa hakimiyet, güçlü topluluk. | C7: Kalori/beslenme takibi ve kiler yönetimi yok; öneriler kişiselleştirilmiyor, envanterle bağlantısız. | D7: Türk mutfağı tarifleri seed veriye dahil ediliyor ve kişisel profil + kiler verisiyle birleştiriliyor.
A8: Global rakiplerin ortak zafiyeti | B8: - | C8: Türkiye pazarındaki yerel ürünlerin (Torku, Ülker, yerel market barkodları ve fişleri) tanınması çok kötü. | D8: Türkçe ürün havuzu kullanıcı katkısıyla (products.source='user') büyütülüyor; unmatched_ingredients ile sözlük kendini besliyor. V3'te Türkçe fiş okuma ile lokal pazarda belirgin üstünlük.
A9: BENZERSIZ DEGER ONERISI (USP) | B9: Kiler + Kalori + Yapay Zeka + Gıda İsrafı dörtlüsünün tek uygulamada birleşmesi. | C9: Rakiplerin hiçbiri bu dört ekseni aynı anda kapatmıyor. | D9: 'Elimdeki malzemelerle, kalori hedefimi aşmadan, sevdiğim tarzda ne pişirebilirim?' sorusuna tek ekranda cevap veren; kullandıkça öğrenen; ve 'bu ay 340 TL çöpe attın' diyerek gıda israfını görünür kılan asistan.

Sheet Risk Yonetimi
A1: RISK YONETIMI | 20 Gunluk Sprintte Plani Bozabilecek Maddeler
A2: Olasilik ve etki: Dusuk / Orta / Yuksek. Her risk icin erken uyari sinyali ve B plani tanimlanmistir.
A3: Risk | B3: Olasılık | C3: Etki | D3: Erken Uyarı Sinyali | E3: Önlem / B Planı
A4: Fiziksel Android test cihazı olmaması | B4: Yüksek | C4: Yüksek | D4: Elde yalnızca iPhone var; Windows'ta iOS derlenemiyor, yani iPhone bu projede kullanılamıyor. | E4: Üç katmanlı çözüm: (1) W1-T13'te BarcodeScanner soyutlaması + FakeBarcodeScanner ile geliştirme cihazdan bağımsız hale getirildi, (2) Android emülatörü Camera->Back: Webcam0 ayarıyla gerçek barkod okuyabiliyor, (3) mobile_scanner analyzeImage ile galeriden barkod okunarak ML Kit yolu doğrulanıyor. W4-T11 için bir günlüğüne gerçek cihaz ödünç alınacak (öncelikle staj yerinden istenecek).
A5: Dart / Flutter'a alışma süresi | B5: Orta | C5: Yüksek | D5: İlk 2 günde basit bir ekranı beklenenden uzun sürede tamamlıyorsan. | E5: Backend (Python/FastAPI) tarafı planın %60'ı ve tamamen tanıdık; sıkışma olursa mobil taraf sadeleştirilir (animasyon, karanlık mod, shimmer çıkarılır), algoritma ve API korunur. Material 3'ün yerleşik bileşenleri özel widget yazma ihtiyacını azaltıyor.
A6: Native build / bağımlılık hataları | B6: Orta | C6: Yüksek | D6: flutter run ilk kez 30 dakikadan uzun sürüyor veya Gradle hatası veriyorsa. | E6: Flutter'a geçiş bu riski zaten belirgin şekilde azalttı (Expo Dev Client zinciri yok). Sıkışma olursa flutter clean + pub cache repair; paket sürümleri pubspec.lock ile sabitlenir ve sprint boyunca flutter upgrade ÇALIŞTIRILMAZ.
A7: Malzeme eşleştirmesinin yanlış sonuç vermesi | B7: Yüksek | C7: Yüksek | D7: Test senaryolarında eşleşme doğruluğu %85'in altına düşerse. | E7: Üç aşamalı eşleştirme (canonical -> alias -> rapidfuzz). W3-T02A ile eşleşmeyenler unmatched_ingredients'a yazılıp hafta sonu sözlüğe ekleniyor. Eşleşmeyen malzeme GRİ gösteriliyor; kullanıcı yanıltılmıyor.
A8: Open Food Facts'te Türk ürünlerinin bulunamaması | B8: Yüksek | C8: Orta | D8: Test edilen 10 yerel barkoddan 4'ünden azı sonuç dönüyorsa. | E8: W2-T05 manuel kayıt fallback'i planda. Demo için 20 popüler ürün önceden products tablosuna seed edilir; sunumda 'boş sonuç' riski sıfırlanır.
A9: Birim dönüşümü hataları | B9: Orta | C9: Yüksek | D9: Stok düşümünde negatif miktar veya beklenmedik büyüklükte düşüm görülürse. | E9: Tüm miktarlar tek temel birimde (g/ml/adet) saklanıyor; dönüşüm tek fonksiyonda toplanıp W4-T09'da 20+ vaka ile test ediliyor. CHECK(quantity_base >= 0) ile negatif stok DB seviyesinde engelleniyor. pantry_events delta toplamı ile pantry_items tutarlılığı test ediliyor.
A10: LLM kotası, gecikmesi veya yanıt kalitesi | B10: Orta | C10: Yüksek | D10: Yanıt süresi 5 saniyeyi geçiyor veya JSON formatı bozuk dönüyorsa. | E10: LLM katmanı soyutlandı; Groq -> OpenAI geçişi tek satır. JSON parse hatasında kural tabanlı öneri listesine düşülür - chatbot çökmez, sadece daha az sohbet eder. llm_cache ile tekrarlayan sorular API'ye hiç gitmez.
A11: Tarif veri setinin kalitesiz/eksik çıkması | B11: Orta | C11: Yüksek | D11: Seed sonrası tariflerin %30'undan fazlasında kalori veya canonical_name eşlemesi boşsa. | E11: Kalite eşiğini geçemeyen tarifler ayıklanır; 40 Türk tarifi elle girildiği için demo her koşulda çalışır. Kalori boşsa ingredients tablosundaki 100 g değerlerinden yaklaşık hesaplanır.
A12: Kapsam kayması (scope creep) | B12: Yüksek | C12: Yüksek | D12: Plan dışı bir özellik için 'sadece yarım gün sürer' denildiğinde. | E12: Fiş OCR, görsel obje tanıma, iOS sürümü ve V2 fikirleri yazılı olarak backlog'a alındı. Yeni her fikir doğrudan V2-V3 Backlog sayfasına yazılır, sprint'e alınmaz. v2'de eklenen 3 görev bilinçli ve gerekçeli tek istisnadır.
A13: Zaman tahminlerinin sapması | B13: Orta | C13: Orta | D13: Herhangi bir haftanın sonunda tamamlanan saat, planlananın %80'inin altındaysa. | E13: Plan 166.5 saat, kapasite 160 saat (6.5 saat fazla). Esnetme payı sırasıyla: W4-T07 (SKT bildirimi, Düşük, 2 saat), W4-T17 (tampon, 2 saat), W3-T16 (algoritma ölçümü, Orta, 2 saat). Gerekirse chatbot arayüzü sadeleştirilir; algoritma ve API korunur.
A14: SQLite foreign key zorlamasının kapalı olması | B14: Orta | C14: Yüksek | D14: Kullanıcı silindiğinde ilişkili kayıtlar duruyorsa. | E14: W1-T05'te PRAGMA foreign_keys=ON event listener'ı ekleniyor ve W4-T12A'da test ile doğrulanıyor. Bu yapılmazsa KVKK veri imha yükümlülüğü karşılanamaz.
... A17: Staj sunumunda demo çökmesi | B17: Düşük | C17: Yüksek | D17: Sunum provasında internet veya API bağımlı bir adım takılıyorsa. | E17: W4-T16'da önceden kaydedilmiş demo videosu hazır tutuluyor; ayrıca çevrimdışı seed veriyle çalışan bir 'demo modu' bayrağı ve FakeBarcodeScanner mevcut.
